kfp_deployer/__init__.py
kfp_deployer/main.py
kfp_deployer-0.1.2.dist-info/entry_points.txt
kfp_deployer-0.1.2.dist-info/LICENSE
kfp_deployer-0.1.2.dist-info/WHEEL
kfp_deployer-0.1.2.dist-info/METADATA
kfp_deployer-0.1.2.dist-info/RECORD
