Metadata-Version: 2.1
Name: kfp-deployer
Version: 0.1.2
Summary: Deploy the KFP ML Pipeline from CLI.
Home-page: https://github.com/reproio/kfp-deployer
Author: Karno
Author-email: karnoroid@gmail.com
Requires-Python: >=3.6,<4.0
Classifier: Programming Language :: Python :: 3
Classifier: Programming Language :: Python :: 3.6
Classifier: Programming Language :: Python :: 3.7
Classifier: Programming Language :: Python :: 3.8
Classifier: Programming Language :: Python :: 3.9
Requires-Dist: kfp (>=1.3.0,<2.0.0)
Requires-Dist: pytz (>=2020.5,<2021.0)
Project-URL: Repository, https://github.com/reproio/kfp-deployer
